mypm/__init__.py
mypm/dbhandler.py
mypm/itemclass.py
mypm/main.py
mypm/optionhandler.py
mypm/parserobj.py
mypm-0.1.2.dist-info/METADATA
mypm-0.1.2.dist-info/WHEEL
mypm-0.1.2.dist-info/entry_points.txt
mypm-0.1.2.dist-info/RECORD
